{ "columns":0,
 "grid":
    {
     "height":1,
     "orientation":"orthogonal",
     "width":1
    },
 "margin":0,
 "name":"more_tiles",
 "spacing":0,
 "tilecount":29,
 "tiledversion":"1.7.2",
 "tileheight":256,
 "tiles":[
        {
         "id":121,
         "image":"tiles\/stoneCenter.png",
         "imageheight":128,
         "imagewidth":128
        }, 
        {
         "id":150,
         "image":"doorClosed_mid.png",
         "imageheight":128,
         "imagewidth":128
        }, 
        {
         "id":151,
         "image":"tiles\/planetCenter.png",
         "imageheight":128,
         "imagewidth":128
        }, 
        {
         "id":154,
         "image":"woodbrick.png",
         "imageheight":128,
         "imagewidth":128
        }, 
        {
         "id":156,
         "image":"tiles\/snowCenter.jpg",
         "imageheight":128,
         "imagewidth":128
        }, 
        {
         "id":159,
         "image":"tiles\/floor thicker.png",
         "imageheight":128,
         "imagewidth":128
        }, 
        {
         "id":161,
         "image":"bed from Morlockhater's Ash's House cropped.png",
         "imageheight":256,
         "imagewidth":256
        }, 
        {
         "id":169,
         "image":"penguin plush.png",
         "imageheight":128,
         "imagewidth":128
        }, 
        {
         "id":170,
         "image":"L chair.png",
         "imageheight":128,
         "imagewidth":128
        }, 
        {
         "id":171,
         "image":"R chair.png",
         "imageheight":128,
         "imagewidth":128
        }, 
        {
         "id":174,
         "image":"toilet.png",
         "imageheight":128,
         "imagewidth":128
        }, 
        {
         "id":175,
         "image":"dresser.png",
         "imageheight":128,
         "imagewidth":128
        }, 
        {
         "id":176,
         "image":"bathtub.png",
         "imageheight":128,
         "imagewidth":256
        }, 
        {
         "id":187,
         "image":"1.png",
         "imageheight":128,
         "imagewidth":128
        }, 
        {
         "id":188,
         "image":"2.png",
         "imageheight":128,
         "imagewidth":128
        }, 
        {
         "id":189,
         "image":"3.png",
         "imageheight":128,
         "imagewidth":128
        }, 
        {
         "id":190,
         "image":"4.png",
         "imageheight":128,
         "imagewidth":128
        }, 
        {
         "id":191,
         "image":"5.png",
         "imageheight":128,
         "imagewidth":128
        }, 
        {
         "id":192,
         "image":"6.png",
         "imageheight":128,
         "imagewidth":128
        }, 
        {
         "id":193,
         "image":"sink_counter_transparent.png",
         "imageheight":256,
         "imagewidth":128
        }, 
        {
         "id":194,
         "image":"piano_transparent.png",
         "imageheight":256,
         "imagewidth":128
        }, 
        {
         "id":195,
         "image":"stove_transparent.png",
         "imageheight":256,
         "imagewidth":128
        }, 
        {
         "id":196,
         "image":"table_transparent.png",
         "imageheight":256,
         "imagewidth":128
        }, 
        {
         "id":197,
         "image":"bathroom_sink_transparent.png",
         "imageheight":128,
         "imagewidth":128
        }, 
        {
         "id":198,
         "image":"bathroom_sink_stand_transparent.png",
         "imageheight":128,
         "imagewidth":128
        }, 
        {
         "id":199,
         "image":"left_chair_fallen.png",
         "imageheight":128,
         "imagewidth":128
        }, 
        {
         "id":200,
         "image":"right_chair_fallen.png",
         "imageheight":128,
         "imagewidth":128
        }, 
        {
         "id":201,
         "image":"piano_chair.png",
         "imageheight":256,
         "imagewidth":128
        }, 
        {
         "id":202,
         "image":"penguin_plush_dead.png",
         "imageheight":128,
         "imagewidth":128
        }],
 "tilewidth":256,
 "type":"tileset",
 "version":"1.6"
}